visuals.py
visuals-1.2.9.dist-info/METADATA
visuals-1.2.9.dist-info/WHEEL
visuals-1.2.9.dist-info/RECORD
