Metadata-Version: 2.3
Name: visuals
Version: 1.2.9
Summary: Create beautiful and colorful designs for your terminal applications
License: Apache-2.0
Author: Zed Cassiel
Author-email: zedpacked@gmail.com
Requires-Python: >=3.10
Classifier: Development Status :: 5 - Production/Stable
Classifier: Intended Audience :: Developers
Classifier: License :: OSI Approved :: Apache Software License
Classifier: Natural Language :: English
Classifier: Operating System :: Microsoft :: Windows
Classifier: Programming Language :: Python :: 3
Classifier: Programming Language :: Python :: 3.10
Classifier: Programming Language :: Python :: 3.11
Classifier: Programming Language :: Python :: 3.12
Classifier: Programming Language :: Python :: 3.13
Classifier: Topic :: Software Development :: Libraries
Requires-Dist: crgb (>=1.0.2,<2.0.0)
Project-URL: Documentation, https://pypi.org/project/visuals
Project-URL: Homepage, https://pypi.org/project/visuals
Project-URL: Source, https://pypi.org/project/visuals/#files
